setup.cfg
setup.py
pyOpsMap/__init__.py
pyOpsMap/ops_map.py
pyOpsMap.egg-info/PKG-INFO
pyOpsMap.egg-info/SOURCES.txt
pyOpsMap.egg-info/dependency_links.txt
pyOpsMap.egg-info/top_level.txt