Metadata-Version: 1.1
Name: pyOpsMap
Version: 0.0.1
Summary: Mapping operators to a dictionary switch
Home-page: https://github.com/tekton/pyOpsMap
Author: Tyler Agee
Author-email: tyler@pyroturtle.com
License: MIT
Keywords: operator
Platform: UNKNOWN
Classifier: Development Status :: 4 - Beta
Classifier: Intended Audience :: Developers
Classifier: License :: OSI Approved :: MIT License
Classifier: Programming Language :: Python
Classifier: Programming Language :: Python :: 2.7
Classifier: Topic :: Software Development :: Libraries :: Python Modules
